json_store/__init__.py
json_store/json_store.py
json_store/shelve2json.py
json_store-4.3.dist-info/METADATA
json_store-4.3.dist-info/WHEEL
json_store-4.3.dist-info/entry_points.txt
json_store-4.3.dist-info/licenses/LICENSE.txt
json_store-4.3.dist-info/RECORD
