Metadata-Version: 2.4
Name: json-store
Version: 4.3
Summary: A shelve-like store using JSON serialization.
Project-URL: Homepage, https://github.com/brainsik/json-store
Project-URL: Repository, https://github.com/brainsik/json-store.git
Project-URL: Issues, https://github.com/brainsik/json-store/issues
Project-URL: Changelog, https://github.com/brainsik/json-store/releases
Author-email: jeremy avnet <json-store@theory.org>
License: Copyright (c) 2010-2025 Jeremy Avnet
License-File: LICENSE.txt
Keywords: json,shelve
Classifier: Development Status :: 5 - Production/Stable
Classifier: Intended Audience :: Developers
Classifier: License :: OSI Approved :: MIT License
Classifier: Operating System :: OS Independent
Classifier: Programming Language :: Python :: 3
Classifier: Programming Language :: Python :: 3.10
Classifier: Programming Language :: Python :: 3.11
Classifier: Programming Language :: Python :: 3.12
Classifier: Programming Language :: Python :: 3.13
Classifier: Programming Language :: Python :: 3.14
Classifier: Programming Language :: Python :: Implementation :: CPython
Classifier: Programming Language :: Python :: Implementation :: PyPy
Classifier: Topic :: Software Development :: Libraries
Requires-Python: >=3.10
